{
  "spartanweaponry:recipes/spartanweaponry.basic/longsword_gold": {
    "criteria": {
      "has_gold_ingot": "2025-05-15 02:37:35 +0000"
    },
    "done": true
  },
  "minecraft:recipes/redstone/lever": {
    "criteria": {
      "has_cobblestone": "2025-05-15 03:21:32 +0000"
    },
    "done": true
  },
  "spartanweaponry:recipes/spartanweaponry.basic/hammer_gold": {
    "criteria": {
      "has_gold_ingot": "2025-05-15 02:37:35 +0000"
    },
    "done": true
  },
  "minecraft:recipes/building_blocks/cobblestone_stairs_from_cobblestone_stonecutting": {
    "criteria": {
      "has_cobblestone": "2025-05-15 03:21:32 +0000"
    },
    "done": true
  },
  "minecraft:recipes/building_blocks/magenta_concrete_powder": {
    "criteria": {
      "has_gravel": "2025-05-15 02:59:23 +0000"
    },
    "done": true
  },
  "minecraft:recipes/misc/writable_book": {
    "criteria": {
      "has_book": "2025-05-15 02:48:29 +0000"
    },
    "done": true
  },
  "minecraft:recipes/redstone/spruce_door": {
    "criteria": {
      "has_planks": "2025-05-15 03:08:50 +0000"
    },
    "done": true
  },
  "securitycraft:recipes/securitycraft/reinforced_andesite_with_vanilla_diorite": {
    "criteria": {
      "has_cobblestone": "2025-05-15 03:21:32 +0000"
    },
    "done": true
  },
  "spartanweaponry:recipes/spartanweaponry.basic/spear_gold": {
    "criteria": {
      "has_gold_ingot": "2025-05-15 02:37:35 +0000"
    },
    "done": true
  },
  "biomesoplenty:recipes/transportation/willow_boat": {
    "criteria": {
      "in_water": "2025-05-15 02:38:01 +0000"
    },
    "done": true
  },
  "securitycraft:recipes/securitycraft/reinforced_spruce_fence": {
    "criteria": {
      "has_stick": "2025-05-15 02:46:54 +0000"
    },
    "done": true
  },
  "minecraft:recipes/building_blocks/lime_concrete_powder": {
    "criteria": {
      "has_gravel": "2025-05-15 02:59:23 +0000"
    },
    "done": true
  },
  "spartanweaponry:recipes/spartanweaponry.basic/longsword_stone": {
    "criteria": {
      "has_cobblestone": "2025-05-15 03:21:32 +0000"
    },
    "done": true
  },
  "minecraft:recipes/building_blocks/yellow_concrete_powder": {
    "criteria": {
      "has_gravel": "2025-05-15 02:59:23 +0000"
    },
    "done": true
  },
  "minecraft:recipes/redstone/spruce_fence_gate": {
    "criteria": {
      "has_planks": "2025-05-15 03:08:50 +0000"
    },
    "done": true
  },
  "spartanweaponry:recipes/spartanweaponry.basic/javelin_wood": {
    "criteria": {
      "has_wood": "2025-05-15 02:46:29 +0000"
    },
    "done": true
  },
  "minecraft:recipes/decorations/crafting_table": {
    "criteria": {
      "has_planks": "2025-05-15 02:46:29 +0000"
    },
    "done": true
  },
  "minecraft:recipes/decorations/campfire": {
    "criteria": {
      "has_stick": "2025-05-15 02:46:54 +0000"
    },
    "done": true
  },
  "minecraft:recipes/tools/golden_hoe": {
    "criteria": {
      "has_gold_ingot": "2025-05-15 02:37:35 +0000"
    },
    "done": true
  },
  "spartanweaponry:recipes/spartanweaponry.basic/flanged_mace_gold": {
    "criteria": {
      "has_gold_ingot": "2025-05-15 02:37:35 +0000"
    },
    "done": true
  },
  "biomesoplenty:recipes/transportation/mahogany_boat": {
    "criteria": {
      "in_water": "2025-05-15 02:38:01 +0000"
    },
    "done": true
  },
  "iceandfire:iceandfire/root": {
    "criteria": {
      "tick": "2025-05-15 02:34:06 +0000"
    },
    "done": true
  },
  "minecraft:recipes/decorations/ladder": {
    "criteria": {
      "has_stick": "2025-05-15 02:46:54 +0000"
    },
    "done": true
  },
  "spartanweaponry:recipes/spartanweaponry.basic/dagger_gold": {
    "criteria": {
      "has_gold_ingot": "2025-05-15 02:37:35 +0000"
    },
    "done": true
  },
  "minecraft:recipes/combat/golden_sword": {
    "criteria": {
      "has_gold_ingot": "2025-05-15 02:37:35 +0000"
    },
    "done": true
  },
  "minecraft:recipes/decorations/chest": {
    "criteria": {
      "has_lots_of_items": "2025-05-15 02:46:38 +0000"
    },
    "done": true
  },
  "minecraft:recipes/building_blocks/brown_concrete_powder": {
    "criteria": {
      "has_gravel": "2025-05-15 02:59:23 +0000"
    },
    "done": true
  },
  "minecraft:recipes/redstone/spruce_button": {
    "criteria": {
      "has_planks": "2025-05-15 03:08:50 +0000"
    },
    "done": true
  },
  "minecraft:recipes/tools/wooden_shovel": {
    "criteria": {
      "has_stick": "2025-05-15 02:46:54 +0000"
    },
    "done": true
  },
  "spartanweaponry:recipes/spartanweaponry.basic/greatsword_gold": {
    "criteria": {
      "has_gold_ingot": "2025-05-15 02:37:35 +0000"
    },
    "done": true
  },
  "biomesoplenty:recipes/transportation/dead_boat": {
    "criteria": {
      "in_water": "2025-05-15 02:38:01 +0000"
    },
    "done": true
  },
  "minecraft:recipes/misc/stick": {
    "criteria": {
      "has_planks": "2025-05-15 02:46:29 +0000"
    },
    "done": true
  },
  "spartanweaponry:recipes/spartanweaponry.basic/parrying_dagger_gold": {
    "criteria": {
      "has_gold_ingot": "2025-05-15 02:37:35 +0000"
    },
    "done": true
  },
  "spartanweaponry:recipes/spartanweaponry.basic/quiver_upgrade_kit_medium": {
    "criteria": {
      "has_gold_ingot": "2025-05-15 02:37:35 +0000"
    },
    "done": true
  },
  "minecraft:recipes/transportation/spruce_boat": {
    "criteria": {
      "in_water": "2025-05-15 02:38:01 +0000"
    },
    "done": true
  },
  "securitycraft:recipes/securitycraft/reinforced_oak_fence": {
    "criteria": {
      "has_stick": "2025-05-15 02:46:54 +0000"
    },
    "done": true
  },
  "minecraft:recipes/misc/flower_banner_pattern": {
    "criteria": {
      "has_oxeye_daisy": "2025-05-15 04:14:45 +0000"
    },
    "done": true
  },
  "minecraft:recipes/tools/flint_and_steel": {
    "criteria": {
      "has_flint": "2025-05-15 02:59:20 +0000"
    },
    "done": true
  },
  "spartanweaponry:recipes/spartanweaponry.basic/saber_wood": {
    "criteria": {
      "has_wood": "2025-05-15 02:46:29 +0000"
    },
    "done": true
  },
  "spartanweaponry:recipes/spartanweaponry.basic/katana_stone": {
    "criteria": {
      "has_cobblestone": "2025-05-15 03:21:32 +0000"
    },
    "done": true
  },
  "spartanweaponry:recipes/spartanweaponry.basic/parrying_dagger_wood": {
    "criteria": {
      "has_wood": "2025-05-15 02:46:29 +0000"
    },
    "done": true
  },
  "spartanweaponry:recipes/spartanweaponry.basic/pole_from_leather": {
    "criteria": {
      "has_stick": "2025-05-15 02:46:54 +0000"
    },
    "done": true
  },
  "spartanweaponry:recipes/spartanweaponry.basic/javelin_gold": {
    "criteria": {
      "has_gold_ingot": "2025-05-15 02:37:35 +0000"
    },
    "done": true
  },
  "minecraft:recipes/building_blocks/emerald_block": {
    "criteria": {
      "has_emerald": "2025-05-15 03:11:09 +0000"
    },
    "done": true
  },
  "minecraft:recipes/food/cake": {
    "criteria": {
      "has_egg": "2025-05-15 02:57:26 +0000"
    },
    "done": true
  },
  "minecraft:recipes/misc/gold_nugget": {
    "criteria": {
      "has_gold_ingot": "2025-05-15 02:37:35 +0000"
    },
    "done": true
  },
  "spartanweaponry:recipes/spartanweaponry.basic/warhammer_gold": {
    "criteria": {
      "has_gold_ingot": "2025-05-15 02:37:35 +0000"
    },
    "done": true
  },
  "securitycraft:recipes/securitycraft/reinforced_dark_oak_fence_gate": {
    "criteria": {
      "has_stick": "2025-05-15 02:46:54 +0000"
    },
    "done": true
  },
  "minecraft:recipes/misc/sugar_from_sugar_cane": {
    "criteria": {
      "has_reeds": "2025-05-15 02:56:07 +0000"
    },
    "done": true
  },
  "securitycraft:recipes/securitycraft/reinforced_andesite_with_vanilla_cobblestone": {
    "criteria": {
      "has_cobblestone": "2025-05-15 03:21:32 +0000"
    },
    "done": true
  },
  "minecraft:husbandry/balanced_diet": {
    "criteria": {
      "baked_potato": "2025-05-15 03:12:02 +0000",
      "apple": "2025-05-15 03:01:08 +0000",
      "bread": "2025-05-15 02:39:43 +0000",
      "golden_apple": "2025-05-15 02:38:30 +0000"
    },
    "done": false
  },
  "minecraft:recipes/tools/wooden_hoe": {
    "criteria": {
      "has_stick": "2025-05-15 02:46:54 +0000"
    },
    "done": true
  },
  "minecraft:recipes/building_blocks/cobblestone_slab": {
    "criteria": {
      "has_cobblestone": "2025-05-15 03:21:32 +0000"
    },
    "done": true
  },
  "spartanweaponry:recipes/spartanweaponry.basic/longbow_gold": {
    "criteria": {
      "has_gold_ingot": "2025-05-15 02:37:35 +0000"
    },
    "done": true
  },
  "minecraft:recipes/building_blocks/cobblestone_stairs": {
    "criteria": {
      "has_cobblestone": "2025-05-15 03:21:32 +0000"
    },
    "done": true
  },
  "spartanweaponry:recipes/spartanweaponry.basic/quarterstaff_gold": {
    "criteria": {
      "has_gold_ingot": "2025-05-15 02:37:35 +0000"
    },
    "done": true
  },
  "spartanweaponry:recipes/spartanweaponry.basic/javelin_stone": {
    "criteria": {
      "has_cobblestone": "2025-05-15 03:21:32 +0000"
    },
    "done": true
  },
  "biomesoplenty:recipes/transportation/magic_boat": {
    "criteria": {
      "in_water": "2025-05-15 02:38:01 +0000"
    },
    "done": true
  },
  "securitycraft:recipes/securitycraft/reinforced_bookshelf": {
    "criteria": {
      "has_book": "2025-05-15 02:48:29 +0000"
    },
    "done": true
  },
  "minecraft:recipes/building_blocks/coarse_dirt": {
    "criteria": {
      "has_gravel": "2025-05-15 02:59:23 +0000"
    },
    "done": true
  },
  "minecraft:recipes/building_blocks/light_gray_concrete_powder": {
    "criteria": {
      "has_gravel": "2025-05-15 02:59:23 +0000"
    },
    "done": true
  },
  "minecraft:recipes/building_blocks/light_blue_concrete_powder": {
    "criteria": {
      "has_gravel": "2025-05-15 02:59:23 +0000"
    },
    "done": true
  },
  "securitycraft:recipes/securitycraft/reinforced_spruce_fence_gate": {
    "criteria": {
      "has_stick": "2025-05-15 02:46:54 +0000"
    },
    "done": true
  },
  "biomesoplenty:recipes/transportation/cherry_boat": {
    "criteria": {
      "in_water": "2025-05-15 02:38:01 +0000"
    },
    "done": true
  },
  "spartanweaponry:recipes/spartanweaponry.basic/flanged_mace_wood": {
    "criteria": {
      "has_wood": "2025-05-15 02:46:29 +0000"
    },
    "done": true
  },
  "biomesoplenty:recipes/transportation/fir_boat": {
    "criteria": {
      "in_water": "2025-05-15 02:38:01 +0000"
    },
    "done": true
  },
  "minecraft:recipes/tools/golden_shovel": {
    "criteria": {
      "has_gold_ingot": "2025-05-15 02:37:35 +0000"
    },
    "done": true
  },
  "minecraft:recipes/building_blocks/pink_concrete_powder": {
    "criteria": {
      "has_gravel": "2025-05-15 02:59:23 +0000"
    },
    "done": true
  },
  "sophisticatedbackpacks:recipes/sophisticatedbackpacks/blasting_upgrade": {
    "criteria": {
      "has_upgrade_base": "2025-05-15 02:37:35 +0000"
    },
    "done": true
  },
  "minecraft:recipes/redstone/oak_fence_gate": {
    "criteria": {
      "has_planks": "2025-05-15 02:46:29 +0000"
    },
    "done": true
  },
  "minecraft:recipes/redstone/lectern": {
    "criteria": {
      "has_book": "2025-05-15 02:48:29 +0000"
    },
    "done": true
  },
  "sophisticatedbackpacks:recipes/sophisticatedbackpacks/auto_smoking_upgrade": {
    "criteria": {
      "has_smoking_upgrade": "2025-05-15 02:37:35 +0000"
    },
    "done": true
  },
  "minecraft:recipes/building_blocks/purple_concrete_powder": {
    "criteria": {
      "has_gravel": "2025-05-15 02:59:23 +0000"
    },
    "done": true
  },
  "spartanweaponry:recipes/spartanweaponry.basic/tomahawk_wood": {
    "criteria": {
      "has_wood": "2025-05-15 02:46:29 +0000"
    },
    "done": true
  },
  "securitycraft:recipes/securitycraft/reinforced_crimson_fence_gate": {
    "criteria": {
      "has_stick": "2025-05-15 02:46:54 +0000"
    },
    "done": true
  },
  "minecraft:recipes/building_blocks/gold_block": {
    "criteria": {
      "has_gold_ingot": "2025-05-15 02:37:35 +0000"
    },
    "done": true
  },
  "securitycraft:recipes/securitycraft/reinforced_birch_fence_gate": {
    "criteria": {
      "has_stick": "2025-05-15 02:46:54 +0000"
    },
    "done": true
  },
  "spartanweaponry:recipes/spartanweaponry.basic/dagger_wood": {
    "criteria": {
      "has_wood": "2025-05-15 02:46:29 +0000"
    },
    "done": true
  },
  "minecraft:story/mine_stone": {
    "criteria": {
      "get_stone": "2025-05-15 03:21:32 +0000"
    },
    "done": true
  },
  "minecraft:recipes/decorations/furnace": {
    "criteria": {
      "has_cobblestone": "2025-05-15 03:21:32 +0000"
    },
    "done": true
  },
  "securitycraft:recipes/securitycraft/reinforced_acacia_fence_gate": {
    "criteria": {
      "has_stick": "2025-05-15 02:46:54 +0000"
    },
    "done": true
  },
  "spartanweaponry:recipes/spartanweaponry.basic/pike_stone": {
    "criteria": {
      "has_cobblestone": "2025-05-15 03:21:32 +0000"
    },
    "done": true
  },
  "securitycraft:recipes/securitycraft/reinforced_jungle_fence": {
    "criteria": {
      "has_stick": "2025-05-15 02:46:54 +0000"
    },
    "done": true
  },
  "minecraft:adventure/sleep_in_bed": {
    "criteria": {
      "slept_in_bed": "2025-05-15 02:39:57 +0000"
    },
    "done": true
  },
  "minecraft:recipes/misc/charcoal": {
    "criteria": {
      "has_log": "2025-05-15 02:46:19 +0000"
    },
    "done": true
  },
  "spartanweaponry:recipes/spartanweaponry.basic/club_wood": {
    "criteria": {
      "has_wood_log": "2025-05-15 02:46:19 +0000"
    },
    "done": true
  },
  "minecraft:recipes/building_blocks/spruce_planks": {
    "criteria": {
      "has_logs": "2025-05-15 03:08:12 +0000"
    },
    "done": true
  },
  "spartanweaponry:recipes/spartanweaponry.basic/glaive_stone": {
    "criteria": {
      "has_cobblestone": "2025-05-15 03:21:32 +0000"
    },
    "done": true
  },
  "minecraft:recipes/tools/wooden_pickaxe": {
    "criteria": {
      "has_stick": "2025-05-15 02:46:54 +0000"
    },
    "done": true
  },
  "sophisticatedbackpacks:recipes/sophisticatedbackpacks/smoking_upgrade_from_smelting_upgrade": {
    "criteria": {
      "has_smelting_upgrade": "2025-05-15 02:37:35 +0000"
    },
    "done": true
  },
  "minecraft:recipes/building_blocks/cobblestone_slab_from_cobblestone_stonecutting": {
    "criteria": {
      "has_cobblestone": "2025-05-15 03:21:32 +0000"
    },
    "done": true
  },
  "minecraft:husbandry/root": {
    "criteria": {
      "consumed_item": "2025-05-15 02:38:30 +0000"
    },
    "done": true
  },
  "spartanweaponry:recipes/spartanweaponry.basic/heavy_crossbow_gold": {
    "criteria": {
      "has_gold_ingot": "2025-05-15 02:37:35 +0000"
    },
    "done": true
  },
  "minecraft:recipes/transportation/birch_boat": {
    "criteria": {
      "in_water": "2025-05-15 02:38:01 +0000"
    },
    "done": true
  },
  "minecraft:recipes/food/golden_apple": {
    "criteria": {
      "has_gold_ingot": "2025-05-15 02:37:35 +0000"
    },
    "done": true
  },
  "spartanweaponry:recipes/spartanweaponry.basic/spear_wood": {
    "criteria": {
      "has_wood": "2025-05-15 02:46:29 +0000"
    },
    "done": true
  },
  "tombstone:adventure/eat_easter_egg_food": {
    "criteria": {
      "coded_trigger": "2025-05-15 02:38:30 +0000"
    },
    "done": true
  },
  "minecraft:recipes/building_blocks/oak_stairs": {
    "criteria": {
      "has_planks": "2025-05-15 02:46:29 +0000"
    },
    "done": true
  },
  "securitycraft:recipes/securitycraft/sonic_security_system": {
    "criteria": {
      "has_stick": "2025-05-15 02:46:54 +0000"
    },
    "done": true
  },
  "minecraft:recipes/building_blocks/green_concrete_powder": {
    "criteria": {
      "has_gravel": "2025-05-15 02:59:23 +0000"
    },
    "done": true
  },
  "spartanweaponry:recipes/spartanweaponry.basic/rapier_stone": {
    "criteria": {
      "has_cobblestone": "2025-05-15 03:21:32 +0000"
    },
    "done": true
  },
  "minecraft:recipes/transportation/acacia_boat": {
    "criteria": {
      "in_water": "2025-05-15 02:38:01 +0000"
    },
    "done": true
  },
  "sophisticatedbackpacks:recipes/sophisticatedbackpacks/auto_blasting_upgrade_from_auto_smelting_upgrade": {
    "criteria": {
      "has_auto_smelting_upgrade": "2025-05-15 02:37:35 +0000"
    },
    "done": true
  },
  "spartanweaponry:recipes/spartanweaponry.basic/handle_from_leather": {
    "criteria": {
      "has_stick": "2025-05-15 02:46:54 +0000"
    },
    "done": true
  },
  "spartanweaponry:recipes/spartanweaponry.basic/boomerang_stone": {
    "criteria": {
      "has_cobblestone": "2025-05-15 03:21:32 +0000"
    },
    "done": true
  },
  "minecraft:recipes/building_blocks/white_concrete_powder": {
    "criteria": {
      "has_gravel": "2025-05-15 02:59:23 +0000"
    },
    "done": true
  },
  "minecraft:recipes/tools/stone_hoe": {
    "criteria": {
      "has_cobblestone": "2025-05-15 03:21:32 +0000"
    },
    "done": true
  },
  "minecraft:recipes/decorations/spruce_fence": {
    "criteria": {
      "has_planks": "2025-05-15 03:08:50 +0000"
    },
    "done": true
  },
  "minecraft:recipes/food/baked_potato_from_smoking": {
    "criteria": {
      "has_potato": "2025-05-15 02:38:54 +0000"
    },
    "done": true
  },
  "spartanweaponry:recipes/spartanweaponry.basic/rapier_gold": {
    "criteria": {
      "has_gold_ingot": "2025-05-15 02:37:35 +0000"
    },
    "done": true
  },
  "spartanweaponry:recipes/spartanweaponry.basic/pike_wood": {
    "criteria": {
      "has_wood": "2025-05-15 02:46:29 +0000"
    },
    "done": true
  },
  "minecraft:adventure/trade": {
    "criteria": {
      "traded": "2025-05-15 03:11:01 +0000"
    },
    "done": true
  },
  "minecraft:recipes/food/baked_potato": {
    "criteria": {
      "has_potato": "2025-05-15 02:38:54 +0000"
    },
    "done": true
  },
  "minecraft:recipes/decorations/fletching_table": {
    "criteria": {
      "has_flint": "2025-05-15 02:59:20 +0000"
    },
    "done": true
  },
  "spartanweaponry:recipes/spartanweaponry.basic/throwing_knife_gold": {
    "criteria": {
      "has_gold_ingot": "2025-05-15 02:37:35 +0000"
    },
    "done": true
  },
  "minecraft:recipes/building_blocks/spruce_stairs": {
    "criteria": {
      "has_planks": "2025-05-15 03:08:50 +0000"
    },
    "done": true
  },
  "spartanweaponry:recipes/spartanweaponry.basic/tomahawk_gold": {
    "criteria": {
      "has_gold_ingot": "2025-05-15 02:37:35 +0000"
    },
    "done": true
  },
  "tombstone:adventure/first_knowledge": {
    "criteria": {
      "coded_trigger": "2025-05-15 02:38:30 +0000"
    },
    "done": true
  },
  "securitycraft:recipes/securitycraft/reinforced_warped_fence_gate": {
    "criteria": {
      "has_stick": "2025-05-15 02:46:54 +0000"
    },
    "done": true
  },
  "spartanweaponry:recipes/spartanweaponry.basic/dagger_stone": {
    "criteria": {
      "has_cobblestone": "2025-05-15 03:21:32 +0000"
    },
    "done": true
  },
  "spartanweaponry:recipes/spartanweaponry.basic/quarterstaff_stone": {
    "criteria": {
      "has_cobblestone": "2025-05-15 03:21:32 +0000"
    },
    "done": true
  },
  "minecraft:recipes/decorations/oak_fence": {
    "criteria": {
      "has_planks": "2025-05-15 02:46:29 +0000"
    },
    "done": true
  },
  "minecraft:recipes/transportation/oak_boat": {
    "criteria": {
      "in_water": "2025-05-15 02:38:01 +0000"
    },
    "done": true
  },
  "spartanweaponry:recipes/spartanweaponry.basic/lance_wood": {
    "criteria": {
      "has_wood": "2025-05-15 02:46:29 +0000"
    },
    "done": true
  },
  "spartanweaponry:recipes/spartanweaponry.basic/warhammer_wood": {
    "criteria": {
      "has_wood": "2025-05-15 02:46:29 +0000"
    },
    "done": true
  },
  "spartanweaponry:recipes/spartanweaponry.basic/handle_from_string": {
    "criteria": {
      "has_stick": "2025-05-15 02:46:54 +0000"
    },
    "done": true
  },
  "spartanweaponry:recipes/spartanweaponry.basic/warhammer_stone": {
    "criteria": {
      "has_cobblestone": "2025-05-15 03:21:32 +0000"
    },
    "done": true
  },
  "minecraft:recipes/food/baked_potato_from_campfire_cooking": {
    "criteria": {
      "has_potato": "2025-05-15 02:38:54 +0000"
    },
    "done": true
  },
  "minecraft:recipes/building_blocks/orange_concrete_powder": {
    "criteria": {
      "has_gravel": "2025-05-15 02:59:23 +0000"
    },
    "done": true
  },
  "minecraft:recipes/building_blocks/oak_slab": {
    "criteria": {
      "has_planks": "2025-05-15 02:46:29 +0000"
    },
    "done": true
  },
  "spartanweaponry:recipes/spartanweaponry.basic/heavy_crossbow_wood": {
    "criteria": {
      "has_wood": "2025-05-15 02:46:29 +0000"
    },
    "done": true
  },
  "minecraft:recipes/building_blocks/cyan_concrete_powder": {
    "criteria": {
      "has_gravel": "2025-05-15 02:59:23 +0000"
    },
    "done": true
  },
  "spartanweaponry:recipes/spartanweaponry.basic/throwing_knife_stone": {
    "criteria": {
      "has_cobblestone": "2025-05-15 03:21:32 +0000"
    },
    "done": true
  },
  "minecraft:recipes/combat/golden_boots": {
    "criteria": {
      "has_gold_ingot": "2025-05-15 02:37:35 +0000"
    },
    "done": true
  },
  "securitycraft:recipes/securitycraft/reinforced_crimson_fence": {
    "criteria": {
      "has_stick": "2025-05-15 02:46:54 +0000"
    },
    "done": true
  },
  "spartanweaponry:recipes/spartanweaponry.basic/scythe_stone": {
    "criteria": {
      "has_cobblestone": "2025-05-15 03:21:32 +0000"
    },
    "done": true
  },
  "minecraft:recipes/tools/wooden_axe": {
    "criteria": {
      "has_stick": "2025-05-15 02:46:54 +0000"
    },
    "done": true
  },
  "minecraft:recipes/decorations/spruce_sign": {
    "criteria": {
      "has_spruce_planks": "2025-05-15 03:08:50 +0000"
    },
    "done": true
  },
  "spartanweaponry:recipes/spartanweaponry.basic/handle_from_wool": {
    "criteria": {
      "has_stick": "2025-05-15 02:46:54 +0000"
    },
    "done": true
  },
  "minecraft:recipes/misc/paper": {
    "criteria": {
      "has_reeds": "2025-05-15 02:56:07 +0000"
    },
    "done": true
  },
  "spartanweaponry:recipes/spartanweaponry.basic/scythe_gold": {
    "criteria": {
      "has_gold_ingot": "2025-05-15 02:37:35 +0000"
    },
    "done": true
  },
  "minecraft:recipes/combat/golden_chestplate": {
    "criteria": {
      "has_gold_ingot": "2025-05-15 02:37:35 +0000"
    },
    "done": true
  },
  "biomesoplenty:recipes/transportation/umbran_boat": {
    "criteria": {
      "in_water": "2025-05-15 02:38:01 +0000"
    },
    "done": true
  },
  "biomesoplenty:recipes/transportation/palm_boat": {
    "criteria": {
      "in_water": "2025-05-15 02:38:01 +0000"
    },
    "done": true
  },
  "spartanweaponry:recipes/spartanweaponry.basic/rapier_wood": {
    "criteria": {
      "has_wood": "2025-05-15 02:46:29 +0000"
    },
    "done": true
  },
  "spartanweaponry:recipes/spartanweaponry.basic/halberd_gold": {
    "criteria": {
      "has_gold_ingot": "2025-05-15 02:37:35 +0000"
    },
    "done": true
  },
  "biomesoplenty:recipes/transportation/redwood_boat": {
    "criteria": {
      "in_water": "2025-05-15 02:38:01 +0000"
    },
    "done": true
  },
  "spartanweaponry:recipes/spartanweaponry.basic/glaive_wood": {
    "criteria": {
      "has_wood": "2025-05-15 02:46:29 +0000"
    },
    "done": true
  },
  "spartanweaponry:recipes/spartanweaponry.basic/battleaxe_gold": {
    "criteria": {
      "has_gold_ingot": "2025-05-15 02:37:35 +0000"
    },
    "done": true
  },
  "minecraft:recipes/misc/red_dye_from_poppy": {
    "criteria": {
      "has_red_flower": "2025-05-15 04:03:04 +0000"
    },
    "done": true
  },
  "spartanweaponry:recipes/spartanweaponry.basic/halberd_wood": {
    "criteria": {
      "has_wood": "2025-05-15 02:46:29 +0000"
    },
    "done": true
  },
  "spartanweaponry:recipes/spartanweaponry.basic/lance_gold": {
    "criteria": {
      "has_gold_ingot": "2025-05-15 02:37:35 +0000"
    },
    "done": true
  },
  "securitycraft:recipes/securitycraft/sc_manual": {
    "criteria": {
      "has_wood": "2025-05-15 02:46:19 +0000"
    },
    "done": true
  },
  "minecraft:recipes/combat/arrow": {
    "criteria": {
      "has_flint": "2025-05-15 02:59:20 +0000"
    },
    "done": true
  },
  "spartanweaponry:recipes/spartanweaponry.basic/pike_gold": {
    "criteria": {
      "has_gold_ingot": "2025-05-15 02:37:35 +0000"
    },
    "done": true
  },
  "minecraft:recipes/building_blocks/spruce_wood": {
    "criteria": {
      "has_log": "2025-05-15 03:08:12 +0000"
    },
    "done": true
  },
  "minecraft:recipes/building_blocks/coal_block": {
    "criteria": {
      "has_coal": "2025-05-15 04:28:33 +0000"
    },
    "done": true
  },
  "mowziesmobs:root": {
    "criteria": {
      "custom_test_name": "2025-05-15 02:34:06 +0000"
    },
    "done": true
  },
  "minecraft:recipes/misc/yellow_dye_from_dandelion": {
    "criteria": {
      "has_yellow_flower": "2025-05-15 04:33:34 +0000"
    },
    "done": true
  },
  "securitycraft:recipes/securitycraft/reinforced_birch_fence": {
    "criteria": {
      "has_stick": "2025-05-15 02:46:54 +0000"
    },
    "done": true
  },
  "minecraft:recipes/redstone/light_weighted_pressure_plate": {
    "criteria": {
      "has_gold_ingot": "2025-05-15 02:37:35 +0000"
    },
    "done": true
  },
  "minecraft:recipes/combat/wooden_sword": {
    "criteria": {
      "has_stick": "2025-05-15 02:46:54 +0000"
    },
    "done": true
  },
  "minecraft:recipes/tools/stone_shovel": {
    "criteria": {
      "has_cobblestone": "2025-05-15 03:21:32 +0000"
    },
    "done": true
  },
  "minecraft:recipes/building_blocks/oak_planks": {
    "criteria": {
      "has_logs": "2025-05-15 02:46:19 +0000"
    },
    "done": true
  },
  "securitycraft:recipes/securitycraft/reinforced_jungle_fence_gate": {
    "criteria": {
      "has_stick": "2025-05-15 02:46:54 +0000"
    },
    "done": true
  },
  "minecraft:recipes/building_blocks/blue_concrete_powder": {
    "criteria": {
      "has_gravel": "2025-05-15 02:59:23 +0000"
    },
    "done": true
  },
  "minecraft:recipes/building_blocks/gray_concrete_powder": {
    "criteria": {
      "has_gravel": "2025-05-15 02:59:23 +0000"
    },
    "done": true
  },
  "tombstone:adventure/root": {
    "criteria": {
      "auto": "2025-05-15 02:34:06 +0000"
    },
    "done": true
  },
  "minecraft:recipes/building_blocks/spruce_slab": {
    "criteria": {
      "has_planks": "2025-05-15 03:08:50 +0000"
    },
    "done": true
  },
  "securitycraft:recipes/securitycraft/reinforced_andesite": {
    "criteria": {
      "has_cobblestone": "2025-05-15 03:21:32 +0000"
    },
    "done": true
  },
  "spartanweaponry:recipes/spartanweaponry.basic/flanged_mace_stone": {
    "criteria": {
      "has_cobblestone": "2025-05-15 03:21:32 +0000"
    },
    "done": true
  },
  "minecraft:recipes/building_blocks/bookshelf": {
    "criteria": {
      "has_book": "2025-05-15 02:48:29 +0000"
    },
    "done": true
  },
  "minecraft:recipes/tools/golden_axe": {
    "criteria": {
      "has_gold_ingot": "2025-05-15 02:37:35 +0000"
    },
    "done": true
  },
  "spartanweaponry:recipes/spartanweaponry.basic/hammer_stone": {
    "criteria": {
      "has_cobblestone": "2025-05-15 03:21:32 +0000"
    },
    "done": true
  },
  "spartanweaponry:recipes/spartanweaponry.basic/tomahawk_stone": {
    "criteria": {
      "has_cobblestone": "2025-05-15 03:21:32 +0000"
    },
    "done": true
  },
  "sophisticatedbackpacks:recipes/sophisticatedbackpacks/blasting_upgrade_from_smelting_upgrade": {
    "criteria": {
      "has_smelting_upgrade": "2025-05-15 02:37:35 +0000"
    },
    "done": true
  },
  "minecraft:recipes/combat/golden_helmet": {
    "criteria": {
      "has_gold_ingot": "2025-05-15 02:37:35 +0000"
    },
    "done": true
  },
  "minecraft:recipes/redstone/oak_pressure_plate": {
    "criteria": {
      "has_planks": "2025-05-15 02:46:29 +0000"
    },
    "done": true
  },
  "spartanweaponry:recipes/spartanweaponry.basic/battleaxe_wood": {
    "criteria": {
      "has_wood": "2025-05-15 02:46:29 +0000"
    },
    "done": true
  },
  "securitycraft:recipes/securitycraft/reinforced_acacia_fence": {
    "criteria": {
      "has_stick": "2025-05-15 02:46:54 +0000"
    },
    "done": true
  },
  "spartanweaponry:recipes/spartanweaponry.basic/battleaxe_stone": {
    "criteria": {
      "has_cobblestone": "2025-05-15 03:21:32 +0000"
    },
    "done": true
  },
  "minecraft:recipes/building_blocks/black_concrete_powder": {
    "criteria": {
      "has_gravel": "2025-05-15 02:59:23 +0000"
    },
    "done": true
  },
  "securitycraft:recipes/securitycraft/laser_block": {
    "criteria": {
      "has_stone": "2025-05-15 03:21:32 +0000"
    },
    "done": true
  },
  "spartanweaponry:recipes/spartanweaponry.basic/boomerang_gold": {
    "criteria": {
      "has_gold_ingot": "2025-05-15 02:37:35 +0000"
    },
    "done": true
  },
  "spartanweaponry:recipes/spartanweaponry.basic/glaive_gold": {
    "criteria": {
      "has_gold_ingot": "2025-05-15 02:37:35 +0000"
    },
    "done": true
  },
  "minecraft:recipes/decorations/cartography_table": {
    "criteria": {
      "has_paper": "2025-05-15 02:48:08 +0000"
    },
    "done": true
  },
  "minecraft:recipes/building_blocks/oak_wood": {
    "criteria": {
      "has_log": "2025-05-15 02:46:19 +0000"
    },
    "done": true
  },
  "minecraft:story/root": {
    "criteria": {
      "crafting_table": "2025-05-15 02:46:38 +0000"
    },
    "done": true
  },
  "minecraft:recipes/combat/crossbow": {
    "criteria": {
      "has_stick": "2025-05-15 02:46:54 +0000"
    },
    "done": true
  },
  "spartanweaponry:recipes/spartanweaponry.basic/throwing_knife_wood": {
    "criteria": {
      "has_wood": "2025-05-15 02:46:29 +0000"
    },
    "done": true
  },
  "spartanweaponry:recipes/spartanweaponry.basic/pole_from_wool": {
    "criteria": {
      "has_stick": "2025-05-15 02:46:54 +0000"
    },
    "done": true
  },
  "sophisticatedbackpacks:recipes/sophisticatedbackpacks/smoking_upgrade": {
    "criteria": {
      "has_upgrade_base": "2025-05-15 02:37:35 +0000"
    },
    "done": true
  },
  "minecraft:recipes/redstone/spruce_pressure_plate": {
    "criteria": {
      "has_planks": "2025-05-15 03:08:50 +0000"
    },
    "done": true
  },
  "minecraft:recipes/decorations/oak_sign": {
    "criteria": {
      "has_oak_planks": "2025-05-15 02:46:29 +0000"
    },
    "done": true
  },
  "minecraft:recipes/redstone/oak_trapdoor": {
    "criteria": {
      "has_planks": "2025-05-15 02:46:29 +0000"
    },
    "done": true
  },
  "spartanweaponry:recipes/spartanweaponry.basic/katana_wood": {
    "criteria": {
      "has_wood": "2025-05-15 02:46:29 +0000"
    },
    "done": true
  },
  "spartanweaponry:recipes/spartanweaponry.basic/scythe_wood": {
    "criteria": {
      "has_wood": "2025-05-15 02:46:29 +0000"
    },
    "done": true
  },
  "spartanweaponry:recipes/spartanweaponry.basic/greatsword_stone": {
    "criteria": {
      "has_cobblestone": "2025-05-15 03:21:32 +0000"
    },
    "done": true
  },
  "minecraft:recipes/building_blocks/red_concrete_powder": {
    "criteria": {
      "has_gravel": "2025-05-15 02:59:23 +0000"
    },
    "done": true
  },
  "betterdungeons:root": {
    "criteria": {
      "always": "2025-05-15 02:34:06 +0000"
    },
    "done": true
  },
  "securitycraft:recipes/securitycraft/reinforced_diorite": {
    "criteria": {
      "has_cobblestone": "2025-05-15 03:21:32 +0000"
    },
    "done": true
  },
  "minecraft:recipes/redstone/oak_button": {
    "criteria": {
      "has_planks": "2025-05-15 02:46:29 +0000"
    },
    "done": true
  },
  "spartanweaponry:recipes/spartanweaponry.basic/greatsword_wood": {
    "criteria": {
      "has_wood": "2025-05-15 02:46:29 +0000"
    },
    "done": true
  },
  "minecraft:recipes/tools/golden_pickaxe": {
    "criteria": {
      "has_gold_ingot": "2025-05-15 02:37:35 +0000"
    },
    "done": true
  },
  "spartanweaponry:recipes/spartanweaponry.basic/katana_gold": {
    "criteria": {
      "has_gold_ingot": "2025-05-15 02:37:35 +0000"
    },
    "done": true
  },
  "minecraft:recipes/building_blocks/stone": {
    "criteria": {
      "has_cobblestone": "2025-05-15 03:21:32 +0000"
    },
    "done": true
  },
  "biomesoplenty:recipes/transportation/hellbark_boat": {
    "criteria": {
      "in_water": "2025-05-15 02:38:01 +0000"
    },
    "done": true
  },
  "spartanweaponry:recipes/spartanweaponry.basic/spear_stone": {
    "criteria": {
      "has_cobblestone": "2025-05-15 03:21:32 +0000"
    },
    "done": true
  },
  "minecraft:adventure/adventuring_time": {
    "criteria": {
      "minecraft:cold_ocean": "2025-05-15 02:38:02 +0000",
      "minecraft:taiga": "2025-05-15 02:42:35 +0000",
      "minecraft:deep_cold_ocean": "2025-05-15 02:38:36 +0000",
      "minecraft:taiga_hills": "2025-05-15 02:43:38 +0000",
      "minecraft:beach": "2025-05-15 02:34:50 +0000",
      "minecraft:river": "2025-05-15 02:35:50 +0000",
      "minecraft:plains": "2025-05-15 02:34:06 +0000"
    },
    "done": false
  },
  "spartanweaponry:recipes/spartanweaponry.basic/saber_gold": {
    "criteria": {
      "has_gold_ingot": "2025-05-15 02:37:35 +0000"
    },
    "done": true
  },
  "minecraft:recipes/misc/book": {
    "criteria": {
      "has_paper": "2025-05-15 02:48:08 +0000"
    },
    "done": true
  },
  "spartanweaponry:recipes/spartanweaponry.basic/boomerang_wood": {
    "criteria": {
      "has_wood": "2025-05-15 02:46:29 +0000"
    },
    "done": true
  },
  "minecraft:recipes/decorations/composter": {
    "criteria": {
      "has_wood_slab": "2025-05-15 03:00:47 +0000"
    },
    "done": true
  },
  "spartanweaponry:recipes/spartanweaponry.basic/quarterstaff_wood": {
    "criteria": {
      "has_wood": "2025-05-15 02:46:29 +0000"
    },
    "done": true
  },
  "tombstone:adventure/find_easter_egg": {
    "criteria": {
      "coded_trigger": "2025-05-15 02:37:35 +0000"
    },
    "done": true
  },
  "spartanweaponry:recipes/spartanweaponry.basic/saber_stone": {
    "criteria": {
      "has_cobblestone": "2025-05-15 03:21:32 +0000"
    },
    "done": true
  },
  "minecraft:recipes/combat/stone_sword": {
    "criteria": {
      "has_cobblestone": "2025-05-15 03:21:32 +0000"
    },
    "done": true
  },
  "spartanweaponry:recipes/spartanweaponry.basic/longbow_wood": {
    "criteria": {
      "has_wood": "2025-05-15 02:46:29 +0000"
    },
    "done": true
  },
  "minecraft:recipes/decorations/barrel": {
    "criteria": {
      "has_planks": "2025-05-15 02:46:29 +0000"
    },
    "done": true
  },
  "securitycraft:recipes/securitycraft/reinforced_warped_fence": {
    "criteria": {
      "has_stick": "2025-05-15 02:46:54 +0000"
    },
    "done": true
  },
  "minecraft:recipes/decorations/cobblestone_wall": {
    "criteria": {
      "has_cobblestone": "2025-05-15 03:21:32 +0000"
    },
    "done": true
  },
  "minecraft:recipes/tools/stone_pickaxe": {
    "criteria": {
      "has_cobblestone": "2025-05-15 03:21:32 +0000"
    },
    "done": true
  },
  "minecraft:recipes/redstone/oak_door": {
    "criteria": {
      "has_planks": "2025-05-15 02:46:29 +0000"
    },
    "done": true
  },
  "securitycraft:recipes/securitycraft/motion_activated_light": {
    "criteria": {
      "has_stick": "2025-05-15 02:46:54 +0000"
    },
    "done": true
  },
  "minecraft:recipes/transportation/jungle_boat": {
    "criteria": {
      "in_water": "2025-05-15 02:38:01 +0000"
    },
    "done": true
  },
  "minecraft:recipes/decorations/cobblestone_wall_from_cobblestone_stonecutting": {
    "criteria": {
      "has_cobblestone": "2025-05-15 03:21:32 +0000"
    },
    "done": true
  },
  "spartanweaponry:recipes/spartanweaponry.basic/halberd_stone": {
    "criteria": {
      "has_cobblestone": "2025-05-15 03:21:32 +0000"
    },
    "done": true
  },
  "spartanweaponry:recipes/spartanweaponry.basic/hammer_wood": {
    "criteria": {
      "has_wood": "2025-05-15 02:46:29 +0000"
    },
    "done": true
  },
  "minecraft:recipes/transportation/dark_oak_boat": {
    "criteria": {
      "in_water": "2025-05-15 02:38:01 +0000"
    },
    "done": true
  },
  "sophisticatedbackpacks:recipes/sophisticatedbackpacks/auto_smoking_upgrade_from_auto_smelting_upgrade": {
    "criteria": {
      "has_auto_smelting_upgrade": "2025-05-15 02:37:35 +0000"
    },
    "done": true
  },
  "spartanweaponry:recipes/spartanweaponry.basic/longsword_wood": {
    "criteria": {
      "has_wood": "2025-05-15 02:46:29 +0000"
    },
    "done": true
  },
  "spartanweaponry:recipes/spartanweaponry.basic/parrying_dagger_stone": {
    "criteria": {
      "has_cobblestone": "2025-05-15 03:21:32 +0000"
    },
    "done": true
  },
  "dungeons_arise:wda_root": {
    "criteria": {
      "WDA": "2025-05-15 02:34:06 +0000"
    },
    "done": true
  },
  "minecraft:recipes/combat/golden_leggings": {
    "criteria": {
      "has_gold_ingot": "2025-05-15 02:37:35 +0000"
    },
    "done": true
  },
  "sophisticatedbackpacks:recipes/sophisticatedbackpacks/auto_blasting_upgrade": {
    "criteria": {
      "has_blasting_upgrade": "2025-05-15 02:37:35 +0000"
    },
    "done": true
  },
  "securitycraft:recipes/securitycraft/reinforced_oak_fence_gate": {
    "criteria": {
      "has_stick": "2025-05-15 02:46:54 +0000"
    },
    "done": true
  },
  "biomesoplenty:recipes/transportation/jacaranda_boat": {
    "criteria": {
      "in_water": "2025-05-15 02:38:01 +0000"
    },
    "done": true
  },
  "spartanweaponry:recipes/spartanweaponry.basic/pole_from_string": {
    "criteria": {
      "has_stick": "2025-05-15 02:46:54 +0000"
    },
    "done": true
  },
  "minecraft:recipes/redstone/spruce_trapdoor": {
    "criteria": {
      "has_planks": "2025-05-15 03:08:50 +0000"
    },
    "done": true
  },
  "spartanweaponry:recipes/spartanweaponry.basic/lance_stone": {
    "criteria": {
      "has_cobblestone": "2025-05-15 03:21:32 +0000"
    },
    "done": true
  },
  "minecraft:recipes/misc/light_gray_dye_from_oxeye_daisy": {
    "criteria": {
      "has_red_flower": "2025-05-15 04:14:45 +0000"
    },
    "done": true
  },
  "minecraft:recipes/decorations/soul_campfire": {
    "criteria": {
      "has_stick": "2025-05-15 02:46:54 +0000"
    },
    "done": true
  },
  "minecraft:recipes/tools/stone_axe": {
    "criteria": {
      "has_cobblestone": "2025-05-15 03:21:32 +0000"
    },
    "done": true
  },
  "securitycraft:recipes/securitycraft/reinforced_dark_oak_fence": {
    "criteria": {
      "has_stick": "2025-05-15 02:46:54 +0000"
    },
    "done": true
  },
  "DataVersion": 2586
}